<annotation>
    <folder>images</folder>
    <filename>IMG_5224.jpeg</filename>
    <size>
        <width>4032</width>
        <height>3024</height>
        <depth>3</depth>
    </size>
    <object>
        <name>plate</name>
        <pose>Unspecified</pose>
        <truncated>0</truncated>
        <occluded>0</occluded>
        <difficult>0</difficult>
        <bndbox>
            <xmin>1687.581665</xmin>
            <ymin>1698.438477</ymin>
            <xmax>1982.508423</xmax>
            <ymax>1813.400513</ymax>
        </bndbox>
    </object>
</annotation>